ws_server/__init__.py
ws_server/__main__.py
ws_server/_version.py
ws_server/server.py
sample_ws_server-0.0.3.dist-info/METADATA
sample_ws_server-0.0.3.dist-info/WHEEL
sample_ws_server-0.0.3.dist-info/entry_points.txt
sample_ws_server-0.0.3.dist-info/top_level.txt
sample_ws_server-0.0.3.dist-info/RECORD
